{
  "metadata": {
    "description": "Grade-level appropriate words for middle school vocabulary building",
    "grades": [6, 7, 8],
    "total_words": 1200,
    "last_updated": "2025-11-11",
    "source": "Educational vocabulary research and common core standards"
  },
  "grade_6": {
    "basic": [
      "analyze", "approach", "area", "assess", "assume", "authority", "available", "benefit",
      "challenge", "character", "column", "communicate", "compare", "component", "consider",
      "construct", "context", "contribute", "coordinate", "core", "corresponding", "culture",
      "design", "detail", "develop", "device", "document", "dominant", "economy", "environment",
      "equipped", "examine", "exist", "explain", "express", "factor", "feature", "focus",
      "function", "furthermore", "gender", "generate", "generation", "globe", "gradually",
      "graphics", "hierarchy", "identify", "independent", "individual", "influence", "interpret",
      "involved", "issue", "labor", "legal", "legislation", "locate", "logical", "maintain",
      "majority", "method", "multiple", "nation", "necessary", "obtain", "occur", "organize",
      "particular", "physical", "policy", "portion", "positive", "potential", "previous",
      "primary", "principle", "process", "provide", "published", "purchase", "range", "region",
      "relevant", "rely", "remove", "represent", "require", "research", "resource", "respond",
      "role", "section", "select", "separate", "sequence", "similar", "solution", "sometimes",
      "source", "specific", "standard", "strategy", "structure", "success", "summary", "survey",
      "symbol", "system", "technique", "technology", "theory", "therefore", "though", "tradition",
      "transfer", "transport", "typical", "united", "university", "variety", "version", "volume",
      "welfare"
    ],
    "advanced": [
      "abundant", "accumulate", "accurate", "achievement", "acquire", "adaptation", "adequate",
      "adjustment", "administration", "advocate", "alternative", "ambiguous", "analysis",
      "approximately", "arbitrary", "automatic", "available", "average", "avoid", "bacteria",
      "barrier", "beneficial", "circumstance", "civil", "climate", "cooperation", "cultural",
      "decade", "decrease", "demonstrate", "dependent", "designate", "dimension", "discipline",
      "distribution", "diverse", "document", "dominant", "economy", "efficient", "eliminate",
      "emphasis", "equivalent", "evaluate", "eventually", "evidence", "expansion", "extensive",
      "fundamental", "generation", "global", "gradual", "guarantee", "hierarchy", "hypothesis",
      "identify", "immense", "impact", "implement", "imply", "initial", "instance", "interact",
      "justify", "layer", "location", "maximum", "minimum", "modify", "monitor", "multiple",
      "negate", "objective", "obtain", "obvious", "opponent", "organize", "perspective",
      "phenomenon", "philosophy", "policy", "portion", "potential", "preliminary", "principle",
      "priority", "procedure", "professional", "proportion", "provoke", "publication",
      "qualify", "reaction", "recovery", "reduction", "regulate", "relevant", "reliable",
      "representative", "resource", "restrict", "revolution", "scenario", "schedule", "section",
      "sector", "select", "sequence", "series", "statistic", "status", "strategy", "sufficient",
      "summary", "survey", "symbolize", "technique", "technology", "temporary", "theory",
      "tradition", "transfer", "transformation", "transport", "underlying", "unique", "universe",
      "valid", "vary", "version", "visible", "volume", "voluntary", "widespread"
    ]
  },
  "grade_7": {
    "basic": [
      "abstract", "academy", "access", "accommodate", "accompany", "accumulate", "adapt", "adequate",
      "adjacent", "adjust", "administration", "adult", "affect", "aggregate", "aid", "albeit",
      "allocate", "alter", "alternative", "ambiguous", "analysis", "annual", "apparent", "append",
      "appreciate", "approach", "appropriate", "approximate", "arbitrary", "architecture", "area",
      "arena", "argue", "arrangement", "articulate", "aspect", "assemble", "assert", "assess",
      "assign", "assist", "assume", "assure", "attach", "attain", "attitude", "attribute",
      "authentic", "authorize", "automatic", "available", "aware", "behalf", "benefit", "bias",
      "bond", "brief", "bulk", "capable", "capacity", "capture", "care", "career", "catalog",
      "category", "cease", "challenge", "characteristic", "characterize", "civil", "clarify",
      "classic", "clause", "code", "coherent", "coincide", "collapse", "colleague", "commence",
      "comment", "commission", "commit", "commodity", "communicate", "community", "compatible",
      "compensate", "compile", "complement", "complex", "component", "comprise", "compute",
      "conceive", "concentrate", "concept", "conclude", "concurrent", "conduct", "confer",
      "conflict", "conform", "consent", "consequent", "consider", "constant", "constitute",
      "constraint", "construct", "consult", "consume", "contact", "contemporary", "context",
      "contract", "contradict", "contrast", "contribute", "coordinate", "core", "corporate",
      "correspond", "council", "couple", "create", "credit", "criteria", "crucial", "culture",
      "currency", "cycle", "database", "debate", "decade", "decide", "decline", "deduce",
      "define", "definite", "demonstrate", "denote", "deny", "depress", "derive", "design",
      "despite", "device", "devise", "devote", "dimension", "diminish", "discrete", "discourse",
      "display", "dispose", "distinct", "distort", "distribute", "diverse", "document", "domain",
      "domestic", "dominate", "draft", "drama", "duration", "dynamic", "economy", "edit", "effect",
      "efficient", "electron", "eliminate", "empirical", "enable", "encounter", "energy", "enforce",
      "enhance", "enormous", "ensure", "entity", "environment", "equate", "equilibrium", "equip",
      "equivalent", "essay", "establish", "estate", "estimate", "ethic", "ethnic", "evaluate",
      "eventual", "evident", "evolve", "exceed", "exclude", "exhibit", "expand", "expert",
      "explicit", "exploit", "export", "extend", "external", "extract", "facilitate", "factor",
      "feature", "federal", "fee", "finite", "flexible", "fluctuate", "focus", "format", "formula",
      "forthcoming", "foundation", "fraction", "fragment", "framework", "function", "fund",
      "fundamental", "furthermore", "gender", "generate", "generation", "globe", "goal", "grade",
      "grant", "guarantee", "guidance", "handle", "hierarchy", "hypothesis", "identical", "identify",
      "ideology", "illustrate", "image", "immigrate", "impact", "implement", "imply", "impose",
      "incentive", "incidence", "include", "income", "incorporate", "index", "indicate", "individual",
      "induce", "inevitable", "infer", "infrastructure", "inherent", "inhibit", "initial", "initiate",
      "injure", "innovate", "input", "insert", "insight", "insist", "inspect", "instance", "institute",
      "instruct", "integral", "integrate", "integrity", "intelligence", "intense", "interact",
      "intermediate", "internal", "interpret", "interval", "intervene", "intimate", "intrinsic",
      "invest", "invoke", "involve", "isolate", "issue", "item", "journal", "justify", "layer",
      "lecture", "legal", "legislate", "levy", "liberal", "license", "likewise", "limitation",
      "linear", "link", "locate", "logic", "maintain", "major", "manipulate", "manual", "margin",
      "mature", "maximize", "mechanism", "media", "mediate", "medical", "medium", "mental", "method",
      "migrate", "military", "minimal", "minimize", "minimum", "minor", "mode", "modify", "module",
      "motive", "multiple", "nation", "negate", "network", "neutral", "nonetheless", "norm", "normal",
      "notion", "notorious", "novel", "nuclear", "objective", "obtain", "obvious", "occupy", "occur",
      "odd", "ongoing", "option", "orient", "outcome", "output", "overall", "overlap", "panel",
      "paradigm", "paragraph", "parallel", "parameter", "participate", "partner", "passive", "patent",
      "pattern", "penalty", "pending", "perceive", "percent", "period", "persist", "perspective",
      "phase", "phenomenon", "philosophy", "physical", "plus", "policy", "portion", "portfolio",
      "positive", "potential", "practitioner", "precede", "precise", "predict", "preliminary",
      "premise", "premium", "prescription", "presentation", "preserve", "pressure", "prevail",
      "primary", "prime", "principal", "principle", "priority", "proceed", "process", "professional",
      "prohibit", "project", "promote", "property", "proportion", "prospect", "protocol", "psychology",
      "publication", "publish", "qualify", "qualitative", "quantity", "quantum", "quarter", "radical",
      "random", "range", "ratio", "rational", "react", "recover", "refine", "regime", "region",
      "register", "regulate", "reinforce", "reject", "relax", "release", "relevant", "reluctant",
      "rely", "remove", "render", "replace", "reply", "represent", "reproduce", "require", "research",
      "reside", "resolve", "resource", "respect", "respective", "respond", "restore", "restrain",
      "restrict", "retain", "reveal", "revenue", "reverse", "revise", "revolution", "rigid", "role",
      "route", "scenario", "schedule", "scheme", "scope", "section", "sector", "secure", "seek",
      "select", "sequence", "series", "sex", "shift", "significant", "similar", "simulate", "site",
      "so-called", "social", "software", "solely", "somewhat", "source", "sovereign",
      "specific", "spectrum", "sphere", "stable", "statistic", "status", "steady", "stimulate",
      "straightforward", "strategy", "stress", "structure", "style", "submit", "subordinate",
      "subsequent", "subsidy", "substitute", "successor", "sufficient", "sum", "summary", "supplement",
      "support", "survey", "survive", "suspend", "sustain", "symbol", "symptom", "syndrome", "system",
      "tactic", "task", "team", "technical", "technique", "technology", "temporary", "tense",
      "terminate", "text", "theme", "theory", "thereby", "thesis", "thorough", "threshold", "thus",
      "topic", "trace", "tradition", "transfer", "transform", "transit", "transmit", "transport",
      "treat", "trend", "trigger", "ultimate", "undergo", "underlying", "undermine", "undertake",
      "uniform", "unify", "unique", "universe", "update", "upgrade", "uphold", "usage", "utility",
      "utilize", "valid", "validity", "value", "variable", "vary", "vehicle", "version", "versus",
      "vertical", "via", "violate", "virtual", "visible", "vision", "visual", "volume", "voluntary",
      "widespread", "willing", "withdraw", "witness", "workforce", "worldwide", "worse", "yet"
    ],
    "advanced": [
      "abstraction", "accommodation", "accumulation", "adaptation", "adjudicate", "aesthetic",
      "affinity", "aggregate", "alignment", "allegiance", "allocation", "amalgamation", "analogous",
      "anomaly", "apparatus", "apprehend", "articulation", "assimilation", "asymmetry", "attribution",
      "authenticity", "autonomy", "axiomatic", "belligerent", "bureaucracy", "catalyst", "causality",
      "cognizant", "cohesion", "commodification", "comprehensive", "conformity", "congruence",
      "conjecture", "constituency", "contingent", "convergence", "corollary", "correlation",
      "corroborate", "cosmology", "credibility", "criterion", "cumulative", "curvature", "cynical",
      "decentralize", "deficit", "delineate", "demographic", "denominator", "dialectical", "dichotomy",
      "differentiation", "diffusion", "dilemma", "diminution", "disparity", "disseminate", "divergence",
      "dogmatic", "duality", "dysfunction", "eclectic", "egalitarian", "elasticity", "empathetic",
      "empiricism", "encapsulation", "encompassing", "entitlement", "epistemology", "equanimity",
      "equivocal", "erudition", "esoteric", "ethnocentric", "eulogize", "euphemism", "exemplify",
      "exhaustive", "expediency", "exploitation", "extrapolate", "facilitation", "fallacious",
      "falsifiable", "feasibility", "fiscal", "flexibility", "fluidity", "formulation", "fortuitous",
      "fragmentation", "functionalism", "generalization", "gratuitous", "hegemony", "heterogeneous",
      "hierarchy", "homogeneous", "humanistic", "idiosyncrasy", "illicit", "immaterial", "immutable",
      "impasse", "impetus", "incongruous", "indeterminate", "inductive", "inertia", "infallible",
      "inflection", "infrastructure", "injunction", "intangible", "interdependence", "interrogation",
      "introspection", "irreducible", "jurisprudence", "juxtaposition", "kinesis", "legitimacy",
      "leverage", "logistical", "marginalization", "maximization", "mediocrity", "methodological",
      "meticulous", "minimalism", "mitigate", "modernity", "modular", "monolithic", "multifaceted",
      "narrative", "nebulous", "nominal", "nonconformity", "normative", "nuance", "nullification",
      "objectivity", "obfuscate", "oligarchy", "omnipotent", "ontology", "optimization", "paradox",
      "particularism", "pathological", "pedagogical", "permutation", "phenomenological", "pluralism",
      "polarization", "postulate", "pragmatism", "precipitate", "predilection", "prescriptive",
      "primordial", "probabilistic", "proclivity", "propensity", "proprietary", "provincialism",
      "qualitative", "quantitative", "radicalism", "ramification", "reciprocity", "reconciliation",
      "recrudescence", "redundancy", "refraction", "relativism", "repartee", "reprehensible",
      "resilient", "retroactive", "retrospective", "reverberation", "rhetorical", "rudimentary",
      "salient", "sanguine", "schematic", "scrutiny", "secularism", "segmentation", "semantics",
      "sequential", "serendipity", "sociological", "sophistication", "spatial", "speculation",
      "standardization", "stochastic", "stratification", "subjectivity", "substantiation", "succinct",
      "superfluous", "supposition", "syllogism", "symmetry", "synchronicity", "systematic",
      "tangential", "taxonomy", "teleological", "temporal", "tenacity", "terminology", "theoretical",
      "totalitarian", "transcendental", "transgression", "transparency", "ubiquitous", "unilateral",
      "universality", "utilitarian", "validation", "veracity", "vicissitude", "vociferous",
      "wholistic", "zeitgeist"
    ]
  },
  "grade_8": {
    "basic": [
      "abdicate", "aberration", "abstain", "abstract", "acclaim", "accolade", "accretion", "adamant",
      "adjective", "advent", "adverse", "advocacy", "aesthetic", "affable", "affinity", "aggravate",
      "aggregate", "agitate", "allegiance", "alleviate", "allocate", "amalgamate", "ambivalent",
      "ameliorate", "amend", "anachronism", "anecdote", "animosity", "antidote", "antithesis",
      "apathy", "aphorism", "apprehension", "arbitrate", "arduous", "artifact", "ascertain",
      "aspersion", "aspirant", "assiduous", "asymmetry", "atrophy", "attribute", "audacity",
      "auspicious", "authentic", "autonomous", "avarice", "banal", "benediction", "benefactor",
      "benevolent", "bequest", "bilateral", "blatant", "blithe", "bourgeois", "brazen", "brevity",
      "brusque", "buttress", "cacophony", "candid", "candor", "capacious", "capitulate", "catalyst",
      "caustic", "censure", "chicanery", "circuitous", "circumscribe", "circumvent", "clairvoyant",
      "cognizant", "cohesive", "collaborate", "commensurate", "commodity", "complacent", "concise",
      "condescend", "conducive", "conflagration", "confluence", "congregate", "conjecture", "connive",
      "consensus", "consequential", "consortium", "constrict", "consume", "contingent", "conundrum",
      "converge", "convivial", "corollary", "corporeal", "corroborate", "credence", "credulous",
      "criterion", "cryptic", "cumulative", "cursory", "cynical", "dearth", "debacle", "decimate",
      "decorum", "defamation", "deferential", "deficit", "delineate", "demagogue", "denigrate",
      "denouement", "derivative", "desiccate", "despot", "deter", "detrimental", "deviate", "diatribe",
      "dichotomy", "diffident", "dilate", "dilatory", "dilettante", "dirge", "disabuse", "discern",
      "discomfit", "discrepancy", "disdain", "disingenuous", "disparage", "disparity", "dissemble",
      "disseminate", "dissident", "distend", "docile", "dogma", "dormant", "duplicity", "duress",
      "eclectic", "edict", "effervescent", "efficacy", "effrontery", "egalitarian", "egregious",
      "elegy", "elicit", "elixir", "eloquent", "emaciate", "embellish", "emollient", "empirical",
      "emulate", "encomium", "encumber", "enervate", "engender", "ephemeral", "epistemology",
      "equanimity", "equivocate", "erudite", "esoteric", "eulogy", "euphemism", "exacerbate",
      "exemplar", "exhort", "exigent", "expedite", "expunge", "extemporaneous", "facilitate",
      "fallacious", "fathom", "fervent", "fidelity", "florid", "flout", "foment", "forbearance",
      "fortuitous", "fractious", "garrulous", "germane", "grandiloquent", "gregarious", "hackneyed",
      "harangue", "hedonism", "hegemony", "hermetic", "heterogeneous", "hierarchy", "homogeneous",
      "iconoclast", "idiosyncratic", "ignominious", "imbue", "immutable", "impasse", "impecunious",
      "impede", "imperious", "imperturbable", "impervious", "impinge", "implacable", "importune",
      "imprecation", "impudent", "inane", "inchoate", "incipient", "incisive", "incongruous",
      "inculcate", "indefatigable", "indigent", "indolent", "ineffable", "ineluctable", "inexorable",
      "infelicitous", "inimitable", "iniquitous", "injunction", "innocuous", "insipid", "insouciant",
      "interdict", "internecine", "intractable", "intransigent", "intrepid", "inure", "invective",
      "inveigle", "inveterate", "irascible", "jettison", "judicious", "juxtapose", "kith", "labile",
      "lachrymose", "laconic", "largesse", "legerdemain", "libertine", "limpid", "litigious",
      "lugubrious", "machiavellian", "maunder", "mellifluous", "mendacious", "meretricious", "mettle",
      "mettlesome", "minatory", "misanthrope", "mitigate", "modicum", "mordant", "multifarious",
      "munificent", "myriad", "nadir", "neologism", "neophyte", "nexus", "nonchalant", "nonplussed",
      "nuance", "obdurate", "obfuscate", "obsequious", "obstinate", "obstreperous", "obtuse",
      "odious", "officious", "olfactory", "onerous", "opprobrium", "ossify", "ostensible", "ostracize",
      "palatable", "palliate", "panacea", "paradigm", "paragon", "pariah", "parsimonious", "partisan",
      "paucity", "pedagogue", "pedantic", "pellucid", "penchant", "penurious", "penury", "peregrinate",
      "perfidious", "perfunctory", "perspicacious", "pertinacious", "phlegmatic", "picaresque",
      "piquant", "platitude", "plethora", "polemic", "portentous", "pragmatic", "prate", "prattle",
      "precept", "precipitate", "precipitous", "precursor", "predilection", "preeminent", "prefatory",
      "prescience", "presumptuous", "preternatural", "prevaricate", "probity", "proclivity", "prodigal",
      "profligate", "propensity", "propinquity", "propitious", "prosaic", "protean", "provident",
      "puerile", "pugnacious", "pulchritude", "punctilious", "pusillanimous", "quagmire", "quaint",
      "quiescent", "quintessential", "quixotic", "raconteur", "ramify", "rapacious", "recalcitrant",
      "recapitulate", "reciprocate", "recondite", "redolent", "redoubtable", "refractory", "refulgent",
      "refute", "remonstrate", "repudiate", "rescind", "resilient", "restitution", "retentive",
      "reverent", "ribald", "rife", "ruse", "sagacious", "salient", "salubrious", "sanctimonious",
      "sanguine", "sardonic", "sartorial", "satiate", "scintilla", "scrupulous", "secular", "sedulous",
      "sine qua non", "solicitous", "soporific", "specious", "spurious", "squander", "stanch", "stolid",
      "stupefy", "stygian", "subjugate", "sublime", "substantiate", "succinct", "superfluous",
      "supercilious", "supine", "supplant", "surreptitious", "sycophant", "syllogism", "tacit",
      "taciturn", "tantamount", "temerity", "tenacious", "tendentious", "tenuous", "timorous",
      "torpid", "tortuous", "transcendent", "transgress", "transient", "translucent", "travesty",
      "trenchant", "truculent", "turgid", "ubiquitous", "unctuous", "undulate", "unremitting",
      "usurp", "vacillate", "vacuous", "vapid", "venerate", "veracious", "verisimilitude", "veritable",
      "vestige", "vexatious", "vicissitude", "vilify", "virulent", "vitriolic", "vituperate", "vivify",
      "vociferous", "wanton", "winsome", "wither", "wizen", "wraith", "xenophobia", "yoke", "zealot",
      "zeitgeist"
    ],
    "advanced": [
      "abnegation", "abstruse", "acquiesce", "adumbrate", "afflatus", "aggrandize", "alacrity",
      "anachronistic", "animadversion", "antinomian", "apotheosis", "approbation", "archipelago",
      "asperity", "assiduity", "astringent", "atavistic", "augury", "baleful", "beatific", "bellicose",
      "bifurcate", "blandishment", "bloviate", "boondoggle", "bowdlerize", "bromide", "calumny",
      "captious", "castigation", "cavil", "chary", "chimera", "choleric", "circumlocution", "claque",
      "cognoscente", "commensurable", "concatenation", "concupiscence", "condign", "contumacious",
      "contumely", "coruscate", "crapulous", "crepuscular", "cunctator", "cupidity", "deleterious",
      "desuetude", "diaphanous", "didactic", "disquisition", "ebullient", "effulgent", "egotistical",
      "epideictic", "epistolary", "equipoise", "eschew", "excoriate", "exegesis", "exiguous", "expiate",
      "extirpate", "faineant", "fatidic", "fatuous", "feckless", "fecund", "flagitious", "flummox",
      "fustian", "gallimaufry", "gambol", "gossamer", "grandee", "gregarious", "grouse", "halcyon",
      "harridan", "hebetude", "hector", "heuristic", "hirsute", "hortatory", "ignoble", "imbricate",
      "impecunious", "impregnable", "improvident", "incommodious", "indefatigable", "indubitable",
      "ineluctable", "ineptitude", "ingenuous", "inimical", "inscrutable", "insouciant", "insuperable",
      "interlocutor", "invidious", "invigilate", "jejune", "jocose", "juggernaut", "kakistocracy",
      "lampoon", "languor", "lascivious", "limn", "logorrhea", "lucubrate", "magnanimity", "magniloquent",
      "maladroit", "malapropism", "malfeasance", "mellifluent", "mendicant", "meretricious", "milieu",
      "misanthropic", "misogyny", "modish", "mordacious", "multitudinous", "nefarious", "noisome",
      "nugatory", "objurgate", "obloquy", "obstreperous", "obtrude", "obviate", "occlude", "opprobrious",
      "overweening", "palaver", "pallid", "panjandrum", "parochial", "pecuniary", "pellucid", "penultimate",
      "peripatetic", "perspicuous", "pertinacious", "philanthropic", "phlegmatic", "picaresque", "pietistic",
      "piquant", "plangent", "plenipotentiary", "plutocratic", "polyglot", "polysyllabic", "prebend",
      "predicament", "prepossessing", "proboscis", "prolix", "propitiate", "puissant", "pyrrhic",
      "quiescence", "quintessence", "raconteur", "rapprochement", "rebarbative", "recherche", "redivivus",
      "remonstrance", "reprobate", "requiescat", "rhapsodic", "rhetorician", "rococo", "rodomontade",
      "ruminant", "salacious", "sangfroid", "sardonic", "saturnine", "scurrilous", "sententious", "simulacrum",
      "solecism", "solicitude", "somnolent", "spasmodic", "stentorian", "stigmatize", "stultify", "subterfuge",
      "supercilious", "surreptitious", "sybaritic", "sycophantic", "tendentious", "terpsichorean", "tetchy",
      "thespian", "tithe", "tocsin", "torrid", "trenchant", "truculent", "turgid", "tyro", "umbrage",
      "unctuous", "unflappable", "unremitting", "usury", "uxorious", "valedictory", "vaunt", "velleity",
      "venal", "verisimilar", "vertiginous", "vindictive", "vitriol", "vociferate", "waggish", "wheedle",
      "winsome", "wistful", "xenophobic", "yahoo", "yammer", "zephyr", "zymotic"
    ]
  }
}
